the_flow/__init__.py
the_flow2025-0.2.28.dist-info/LICENSE
the_flow2025-0.2.28.dist-info/METADATA
the_flow2025-0.2.28.dist-info/WHEEL
the_flow2025-0.2.28.dist-info/entry_points.txt
the_flow2025-0.2.28.dist-info/RECORD
