Metadata-Version: 2.1
Name: the-flow2025
Version: 0.2.28
Summary: Personal automation framework (The Flow)
Home-page: https://github.com/00groundsfalloff/the-flow
License: MIT
Keywords: automation,productivity,chatgpt,obsidian,ticktick
Author: Benjamin Swancutt
Author-email: benswancutt99@gmail.com
Requires-Python: >=3.10,<4.0
Classifier: License :: OSI Approved :: MIT License
Classifier: Operating System :: OS Independent
Classifier: Programming Language :: Python :: 3
Classifier: Programming Language :: Python :: 3.10
Classifier: Programming Language :: Python :: 3.11
Classifier: Programming Language :: Python :: 3.12
Classifier: Programming Language :: Python :: 3 :: Only
Requires-Dist: chromadb (>=1.0.7,<2.0.0)
Requires-Dist: click (>=8.1.7,<9.0.0)
Requires-Dist: openai (>=1.77.0,<2.0.0)
Project-URL: Repository, https://github.com/00groundsfalloff/the-flow
